mcp_oauth/__init__.py
mcp_oauth/start_env.py
mcp_oauth/client/oauth_client.py
mcp_oauth/client/client_provider/client_provider.py
mcp_oauth/client/features/callbacks.py
mcp_oauth/client/features/token_storage.py
mcp_oauth/server/oauth_server.py
mcp_oauth/server/quick_server.py
mcp_oauth/server/auth_provider/html_page.py
mcp_oauth/server/auth_provider/simple_auth_provider.py
mcp_oauth/server/features/functions.py
mcp_oauth/server/token_verifier/token_verifier.py
mcp_oauth/utils/criptografy_key.py
mcp_oauth/utils/read_write2file.py
mcp_oauth-0.0.5.dist-info/licenses/license
mcp_oauth-0.0.5.dist-info/METADATA
mcp_oauth-0.0.5.dist-info/WHEEL
mcp_oauth-0.0.5.dist-info/top_level.txt
mcp_oauth-0.0.5.dist-info/RECORD
