Metadata-Version: 2.4
Name: mcp-oauth
Version: 0.0.5
Summary: Simple OAuth system integrated with "mcp[cli]"
Author-email: Raúl Beltrán Gómez <rb58853@gmail.com>
License-Expression: MIT
Project-URL: Homepage, https://github.com/rb58853/mcp-oauth
Project-URL: Issues, https://github.com/rb58853/mcp-oauth/issues
Classifier: Programming Language :: Python :: 3
Classifier: Operating System :: OS Independent
Requires-Python: >=3.11
License-File: license
Requires-Dist: starlette
Requires-Dist: uvicorn
Requires-Dist: mcp[cli]
Requires-Dist: python-jose
Requires-Dist: requests
Requires-Dist: dotenv
Dynamic: license-file
